tokenized/__init__.py
tokenized/tokenizer.py
tokenize_text-0.2.32.dist-info/METADATA
tokenize_text-0.2.32.dist-info/WHEEL
tokenize_text-0.2.32.dist-info/top_level.txt
tokenize_text-0.2.32.dist-info/RECORD
